django_filter_drf_camel_case/__init__.py
django_filter_drf_camel_case/backend.py
django_filter_drf_camel_case/filters.py
django_filter_drf_camel_case/regex.py
django_filter_drf_camel_case/spectacular/__init__.py
django_filter_drf_camel_case/spectacular/extensions.py
django_filter_drf_camel_case-0.1.0.dist-info/LICENSE
django_filter_drf_camel_case-0.1.0.dist-info/WHEEL
django_filter_drf_camel_case-0.1.0.dist-info/METADATA
django_filter_drf_camel_case-0.1.0.dist-info/RECORD
