Metadata-Version: 2.1
Name: django-filter-drf-camel-case
Version: 0.1.0
Summary: A collection of utility classes that make using camel cased query parameters easier with Django REST Framework and django-filter
License: MIT
Author: Chris Muthig
Author-email: camuthig@gmail.com
Requires-Python: >=3.7,<4.0
Classifier: License :: OSI Approved :: MIT License
Classifier: Programming Language :: Python :: 3
Classifier: Programming Language :: Python :: 3.7
Classifier: Programming Language :: Python :: 3.8
Classifier: Programming Language :: Python :: 3.9
Classifier: Programming Language :: Python :: 3.10
Classifier: Programming Language :: Python :: 3.11
Requires-Dist: django-filter (>=2.0,<23.0)
Requires-Dist: djangorestframework (>=3.0,<4.0)
Requires-Dist: djangorestframework-camel-case (>=1.0,<2.0)
Requires-Dist: drf-spectacular[drf-spectactular] (>=0.24.0,<0.25.0)
